AUTHORS.rst
CONTRIBUTING.rst
HISTORY.rst
LICENSE
MANIFEST.in
README.rst
setup.cfg
setup.py
django_slds/__init__.py
django_slds/urls.py
django_slds.egg-info/PKG-INFO
django_slds.egg-info/SOURCES.txt
django_slds.egg-info/dependency_links.txt
django_slds.egg-info/not-zip-safe
django_slds.egg-info/top_level.txt
django_slds/static/slds/assets/fonts/SalesforceSans-Bold.ttf
django_slds/static/slds/assets/fonts/SalesforceSans-BoldItalic.ttf
django_slds/static/slds/assets/fonts/SalesforceSans-Italic.ttf
django_slds/static/slds/assets/fonts/SalesforceSans-Light.ttf
django_slds/static/slds/assets/fonts/SalesforceSans-LightItalic.ttf
django_slds/static/slds/assets/fonts/SalesforceSans-Regular.ttf
django_slds/static/slds/assets/fonts/SalesforceSans-Thin.ttf
django_slds/static/slds/assets/fonts/SalesforceSans-ThinItalic.ttf
django_slds/static/slds/assets/fonts/webfonts/SalesforceSans-Bold.eot
django_slds/static/slds/assets/fonts/webfonts/SalesforceSans-Bold.svg
django_slds/static/slds/assets/fonts/webfonts/SalesforceSans-Bold.woff
django_slds/static/slds/assets/fonts/webfonts/SalesforceSans-Bold.woff2
django_slds/static/slds/assets/fonts/webfonts/SalesforceSans-BoldItalic.eot
django_slds/static/slds/assets/fonts/webfonts/SalesforceSans-BoldItalic.svg
django_slds/static/slds/assets/fonts/webfonts/SalesforceSans-BoldItalic.woff
django_slds/static/slds/assets/fonts/webfonts/SalesforceSans-BoldItalic.woff2
django_slds/static/slds/assets/fonts/webfonts/SalesforceSans-Italic.eot
django_slds/static/slds/assets/fonts/webfonts/SalesforceSans-Italic.svg
django_slds/static/slds/assets/fonts/webfonts/SalesforceSans-Italic.woff
django_slds/static/slds/assets/fonts/webfonts/SalesforceSans-Italic.woff2
django_slds/static/slds/assets/fonts/webfonts/SalesforceSans-Light.eot
django_slds/static/slds/assets/fonts/webfonts/SalesforceSans-Light.svg
django_slds/static/slds/assets/fonts/webfonts/SalesforceSans-Light.woff
django_slds/static/slds/assets/fonts/webfonts/SalesforceSans-Light.woff2
django_slds/static/slds/assets/fonts/webfonts/SalesforceSans-LightItalic.eot
django_slds/static/slds/assets/fonts/webfonts/SalesforceSans-LightItalic.svg
